maai/__init__.py
maai/encoder.py
maai/encoder_components.py
maai/input.py
maai/model.py
maai/modules.py
maai/objective.py
maai/output.py
maai/util.py
maai/models/config.py
maai/models/vap.py
maai/models/vap_bc.py
maai/models/vap_bc_2type.py
maai/models/vap_nod.py
maai/models/vap_prompt.py
maai-0.1.16.dist-info/METADATA
maai-0.1.16.dist-info/WHEEL
maai-0.1.16.dist-info/licenses/LICENSE
maai-0.1.16.dist-info/RECORD
