Metadata-Version: 2.4
Name: maai
Version: 0.1.16
Summary: Real-time and Continuous Non-Linguistic Behavior (Maai) Generation Software
Project-URL: Homepage, https://github.com/MaAI-Kyoto/MaAI
Author-email: MaAI team <inoue@sap.ist.i.kyoto-u.ac.jp>
License: MIT License
License-File: LICENSE
Requires-Python: >=3.10
Requires-Dist: einops>=0.7.0
Requires-Dist: fastapi>=0.111.0
Requires-Dist: huggingface-hub
Requires-Dist: matplotlib
Requires-Dist: numpy
Requires-Dist: pyaudio
Requires-Dist: pydub
Requires-Dist: pygame
Requires-Dist: seaborn
Requires-Dist: soundfile
Requires-Dist: torch>=2.2.0
